geoipsets/VERSION
geoipsets/__init__.py
geoipsets/__main__.py
geoipsets/dbip.py
geoipsets/maxmind.py
geoipsets/utils.py
geoipsets-2.4.0.dist-info/METADATA
geoipsets-2.4.0.dist-info/WHEEL
geoipsets-2.4.0.dist-info/entry_points.txt
geoipsets-2.4.0.dist-info/top_level.txt
geoipsets-2.4.0.dist-info/RECORD
