Metadata-Version: 2.1
Name: geoipsets
Version: 2.4.0
Summary: Utility to build country-specific IP sets for ipset/iptables and nftables.
Home-page: https://github.com/chr0mag/geoipsets
License: GPLv3
Classifier: Operating System :: POSIX :: Linux
Classifier: License :: OSI Approved :: GNU General Public License v3 (GPLv3)
Classifier: Programming Language :: Python :: 3
Classifier: Programming Language :: Python :: 3.9
Classifier: Programming Language :: Python :: 3.10
Classifier: Programming Language :: Python :: 3.11
Classifier: Programming Language :: Python :: 3.12
Classifier: Programming Language :: Python :: 3.13
Requires-Dist: requests
Requires-Dist: beautifulsoup4
